lloom/__init__.py
lloom/lloom.py
lloom-0.0.1.dist-info/LICENSE
lloom-0.0.1.dist-info/METADATA
lloom-0.0.1.dist-info/WHEEL
lloom-0.0.1.dist-info/top_level.txt
lloom-0.0.1.dist-info/RECORD
