Metadata-Version: 2.1
Name: lloom
Version: 0.0.1
License-File: LICENSE
Requires-Dist: tiktoken
Requires-Dist: pydantic
